{
  "sheetsById": {
    "Scene": {
      "staticOverrides": {
        "byObject": {
          "camera": {
            "position": {
              "x": -1.677055762038358,
              "y": 3.0825777285477156,
              "z": 0.15314899224098677
            },
            "rotation": {
              "x": 1.3393761743089114,
              "y": -1.4101310576669481,
              "z": 1.3364655037576598
            }
          },
          "potato-theathre-key": {
            "position": {
              "x": -6.462491101371063,
              "y": 1.5467153826051598,
              "z": 0.31880150983661926
            }
          }
        }
      },
      "sequence": {
        "subUnitsPerUnit": 30,
        "length": 10,
        "type": "PositionalSequence",
        "tracksByObject": {
          "camera": {
            "trackData": {
              "fpXOXqXAyG": {
                "type": "BasicKeyframedTrack",
                "__debugName": "camera:[\"position\",\"x\"]",
                "keyframes": [
                  {
                    "id": "HDVSLjkgYL",
                    "position": 0,
                    "connectedRight": true,
                    "handles": [
                      0.5,
                      1,
                      0.5,
                      0
                    ],
                    "type": "bezier",
                    "value": -8.106772805417952
                  },
                  {
                    "id": "CVVuj0tj1N",
                    "position": 0.967,
                    "connectedRight": true,
                    "handles": [
                      0.5,
                      1,
                      0.5,
                      0
                    ],
                    "type": "bezier",
                    "value": -7.944951468703038
                  },
                  {
                    "id": "CRyC2pdbug",
                    "position": 1,
                    "connectedRight": true,
                    "handles": [
                      0.5,
                      1,
                      0.5,
                      0
                    ],
                    "type": "bezier",
                    "value": -7.95190743845441
                  },
                  {
                    "id": "KdsV-T3puo",
                    "position": 1.7,
                    "connectedRight": true,
                    "handles": [
                      0.5,
                      1,
                      0.5,
                      0
                    ],
                    "type": "bezier",
                    "value": -10.415591969764627
                  },
                  {
                    "id": "dTkhTUjF4w",
                    "position": 2.2,
                    "connectedRight": true,
                    "handles": [
                      0.5,
                      1,
                      0.5,
                      0
                    ],
                    "type": "bezier",
                    "value": -17.78969091268893
                  },
                  {
                    "id": "E90v6AKeIx",
                    "position": 2.233,
                    "connectedRight": true,
                    "handles": [
                      0.5,
                      1,
                      0.5,
                      0
                    ],
                    "type": "bezier",
                    "value": -17.82489953127648
                  },
                  {
                    "id": "v8g-R7DGDn",
                    "position": 3.033,
                    "connectedRight": true,
                    "handles": [
                      0.5,
                      1,
                      0.5,
                      0
                    ],
                    "type": "bezier",
                    "value": 12.00990932739571
                  },
                  {
                    "id": "QNC0MmFGmP",
                    "position": 3.5,
                    "connectedRight": true,
                    "handles": [
                      0.5,
                      1,
                      0.5,
                      0
                    ],
                    "type": "bezier",
                    "value": 25.36063221957271
                  },
                  {
                    "id": "HXVkzCYjtS",
                    "position": 4.433,
                    "connectedRight": true,
                    "handles": [
                      0.5,
                      1,
                      0.5,
                      0
                    ],
                    "type": "bezier",
                    "value": 4.357186914558069
                  },
                  {
                    "id": "MHjfik3JKa",
                    "position": 4.933,
                    "connectedRight": true,
                    "handles": [
                      0.5,
                      1,
                      0.5,
                      0
                    ],
                    "type": "bezier",
                    "value": -7.253806123030737
                  },
                  {
                    "id": "jiOy_QwLz0",
                    "position": 5.133,
                    "connectedRight": true,
                    "handles": [
                      0.5,
                      1,
                      0.5,
                      0
                    ],
                    "type": "bezier",
                    "value": -13.858207289052642
                  },
                  {
                    "id": "KqZqqnLl6x",
                    "position": 5.3,
                    "connectedRight": true,
                    "handles": [
                      0.5,
                      1,
                      0.5,
                      0
                    ],
                    "type": "bezier",
                    "value": -14.716092762797272
                  },
                  {
                    "id": "8aLorm6_S8",
                    "position": 5.533,
                    "connectedRight": true,
                    "handles": [
                      0.5,
                      1,
                      0.5,
                      0
                    ],
                    "type": "bezier",
                    "value": -22.995851615526473
                  },
                  {
                    "id": "8EPTF_Sm4G",
                    "position": 7.933,
                    "connectedRight": true,
                    "handles": [
                      0.5,
                      1,
                      0.5,
                      0
                    ],
                    "type": "bezier",
                    "value": -49.197269742212086
                  },
                  {
                    "id": "-OWr2C8MPB",
                    "position": 8.333,
                    "connectedRight": true,
                    "handles": [
                      0.5,
                      1,
                      0.5,
                      0
                    ],
                    "type": "bezier",
                    "value": -57.238729680249165
                  },
                  {
                    "id": "gsfboUaDoa",
                    "position": 8.667,
                    "connectedRight": true,
                    "handles": [
                      0.5,
                      1,
                      0.5,
                      0
                    ],
                    "type": "bezier",
                    "value": -66.89998590408119
                  },
                  {
                    "id": "Cwyrv1K-i0",
                    "position": 9.367,
                    "connectedRight": true,
                    "handles": [
                      0.5,
                      1,
                      0.5,
                      0
                    ],
                    "type": "bezier",
                    "value": -76.48419201996127
                  },
                  {
                    "id": "uHGbLAEKqI",
                    "position": 10,
                    "connectedRight": true,
                    "handles": [
                      0.5,
                      1,
                      0.5,
                      0
                    ],
                    "type": "bezier",
                    "value": -80.40376754325803
                  }
                ]
              },
              "yohFLt71No": {
                "type": "BasicKeyframedTrack",
                "__debugName": "camera:[\"position\",\"y\"]",
                "keyframes": [
                  {
                    "id": "NOeImmeIVk",
                    "position": 0,
                    "connectedRight": true,
                    "handles": [
                      0.5,
                      1,
                      0.5,
                      0
                    ],
                    "type": "bezier",
                    "value": 4.5990132915433675
                  },
                  {
                    "id": "PzGBGR6Cau",
                    "position": 0.967,
                    "connectedRight": true,
                    "handles": [
                      0.5,
                      1,
                      0.5,
                      0
                    ],
                    "type": "bezier",
                    "value": 3.571733922812986
                  },
                  {
                    "id": "V72CBwkPre",
                    "position": 1,
                    "connectedRight": true,
                    "handles": [
                      0.5,
                      1,
                      0.5,
                      0
                    ],
                    "type": "bezier",
                    "value": 3.5706366754832426
                  },
                  {
                    "id": "sUwlHEDLWo",
                    "position": 1.7,
                    "connectedRight": true,
                    "handles": [
                      0.5,
                      1,
                      0.5,
                      0
                    ],
                    "type": "bezier",
                    "value": 3.1820105931491898
                  },
                  {
                    "id": "E1R6b-o-1j",
                    "position": 2.2,
                    "connectedRight": true,
                    "handles": [
                      0.5,
                      1,
                      0.5,
                      0
                    ],
                    "type": "bezier",
                    "value": 2.0188068036573985
                  },
                  {
                    "id": "dnvpcQ5V6I",
                    "position": 2.233,
                    "connectedRight": true,
                    "handles": [
                      0.5,
                      1,
                      0.5,
                      0
                    ],
                    "type": "bezier",
                    "value": 2.013252932075148
                  },
                  {
                    "id": "shk6vlme2N",
                    "position": 3.033,
                    "connectedRight": true,
                    "handles": [
                      0.5,
                      1,
                      0.5,
                      0
                    ],
                    "type": "bezier",
                    "value": 12.436629555163659
                  },
                  {
                    "id": "aH-kkKnmxM",
                    "position": 3.5,
                    "connectedRight": true,
                    "handles": [
                      0.5,
                      1,
                      0.5,
                      0
                    ],
                    "type": "bezier",
                    "value": 12.834739698565658
                  },
                  {
                    "id": "SoU2-T2IY8",
                    "position": 4.433,
                    "connectedRight": true,
                    "handles": [
                      0.5,
                      1,
                      0.5,
                      0
                    ],
                    "type": "bezier",
                    "value": 6.134955173274018
                  },
                  {
                    "id": "8QRQXJB0zY",
                    "position": 4.933,
                    "connectedRight": true,
                    "handles": [
                      0.5,
                      1,
                      0.5,
                      0
                    ],
                    "type": "bezier",
                    "value": 4.860381501191448
                  },
                  {
                    "id": "gaCpAPDVKg",
                    "position": 5.133,
                    "connectedRight": true,
                    "handles": [
                      0.5,
                      1,
                      0.5,
                      0
                    ],
                    "type": "bezier",
                    "value": 4.657681570970534
                  },
                  {
                    "id": "P4KDAH3RzL",
                    "position": 5.3,
                    "connectedRight": true,
                    "handles": [
                      0.5,
                      1,
                      0.5,
                      0
                    ],
                    "type": "bezier",
                    "value": 4.910577668528036
                  },
                  {
                    "id": "0Oa375OnzC",
                    "position": 5.533,
                    "connectedRight": true,
                    "handles": [
                      0.5,
                      1,
                      0.5,
                      0
                    ],
                    "type": "bezier",
                    "value": 5.295825987178132
                  },
                  {
                    "id": "6XM_dq5wZ7",
                    "position": 7.933,
                    "connectedRight": true,
                    "handles": [
                      0.5,
                      1,
                      0.5,
                      0
                    ],
                    "type": "bezier",
                    "value": 5.457793092095096
                  },
                  {
                    "id": "aKzoDS-25k",
                    "position": 8.333,
                    "connectedRight": true,
                    "handles": [
                      0.5,
                      1,
                      0.5,
                      0
                    ],
                    "type": "bezier",
                    "value": 5.457793092095096
                  },
                  {
                    "id": "8P8cawEsq-",
                    "position": 8.667,
                    "connectedRight": true,
                    "handles": [
                      0.5,
                      1,
                      0.5,
                      0
                    ],
                    "type": "bezier",
                    "value": 5.457793092095096
                  },
                  {
                    "id": "tIzMQbngSz",
                    "position": 9.367,
                    "connectedRight": true,
                    "handles": [
                      0.5,
                      1,
                      0.5,
                      0
                    ],
                    "type": "bezier",
                    "value": 5.457793092095096
                  },
                  {
                    "id": "_tqXqr9-NB",
                    "position": 10,
                    "connectedRight": true,
                    "handles": [
                      0.5,
                      1,
                      0.5,
                      0
                    ],
                    "type": "bezier",
                    "value": 1.9993031191483395
                  }
                ]
              },
              "W5pHjE1nGy": {
                "type": "BasicKeyframedTrack",
                "__debugName": "camera:[\"position\",\"z\"]",
                "keyframes": [
                  {
                    "id": "0sk6_t1GQB",
                    "position": 0,
                    "connectedRight": true,
                    "handles": [
                      0.5,
                      1,
                      0.5,
                      0
                    ],
                    "type": "bezier",
                    "value": 0.46688783479380136
                  },
                  {
                    "id": "cYcySQmxr9",
                    "position": 0.967,
                    "connectedRight": true,
                    "handles": [
                      0.5,
                      1,
                      0.5,
                      0
                    ],
                    "type": "bezier",
                    "value": 0.4608728422251281
                  },
                  {
                    "id": "V4PCqfHM3O",
                    "position": 1,
                    "connectedRight": true,
                    "handles": [
                      0.5,
                      1,
                      0.5,
                      0
                    ],
                    "type": "bezier",
                    "value": 0.46113139963919847
                  },
                  {
                    "id": "bXVsgABcaj",
                    "position": 1.7,
                    "connectedRight": true,
                    "handles": [
                      0.5,
                      1,
                      0.5,
                      0
                    ],
                    "type": "bezier",
                    "value": 0.5527079769201931
                  },
                  {
                    "id": "sPdR35l765",
                    "position": 2.2,
                    "connectedRight": true,
                    "handles": [
                      0.5,
                      1,
                      0.5,
                      0
                    ],
                    "type": "bezier",
                    "value": 0.8268074945906974
                  },
                  {
                    "id": "abLmM6RcIn",
                    "position": 2.233,
                    "connectedRight": true,
                    "handles": [
                      0.5,
                      1,
                      0.5,
                      0
                    ],
                    "type": "bezier",
                    "value": 0.8281162192833531
                  },
                  {
                    "id": "PjhEzD4GyP",
                    "position": 3.033,
                    "connectedRight": true,
                    "handles": [
                      0.5,
                      1,
                      0.5,
                      0
                    ],
                    "type": "bezier",
                    "value": 1.3934569788622955
                  },
                  {
                    "id": "OkXY8WkXvC",
                    "position": 3.5,
                    "connectedRight": true,
                    "handles": [
                      0.5,
                      1,
                      0.5,
                      0
                    ],
                    "type": "bezier",
                    "value": -0.7258770846646623
                  },
                  {
                    "id": "2gtpL6_0dM",
                    "position": 4.433,
                    "connectedRight": true,
                    "handles": [
                      0.5,
                      1,
                      0.5,
                      0
                    ],
                    "type": "bezier",
                    "value": 0.011811125614133444
                  },
                  {
                    "id": "GfdjSb0mL5",
                    "position": 4.933,
                    "connectedRight": true,
                    "handles": [
                      0.5,
                      1,
                      0.5,
                      0
                    ],
                    "type": "bezier",
                    "value": 0.6258162815236703
                  },
                  {
                    "id": "CvAm4suzHx",
                    "position": 5.133,
                    "connectedRight": true,
                    "handles": [
                      0.5,
                      1,
                      0.5,
                      0
                    ],
                    "type": "bezier",
                    "value": 0.7234636792255128
                  },
                  {
                    "id": "hpyQ3-SkxK",
                    "position": 5.3,
                    "connectedRight": true,
                    "handles": [
                      0.5,
                      1,
                      0.5,
                      0
                    ],
                    "type": "bezier",
                    "value": 0.8231212029248112
                  },
                  {
                    "id": "QoGrAkjJ6G",
                    "position": 5.533,
                    "connectedRight": true,
                    "handles": [
                      0.5,
                      1,
                      0.5,
                      0
                    ],
                    "type": "bezier",
                    "value": 0.9749341166739345
                  },
                  {
                    "id": "OtK3HwnoSo",
                    "position": 7.933,
                    "connectedRight": true,
                    "handles": [
                      0.5,
                      1,
                      0.5,
                      0
                    ],
                    "type": "bezier",
                    "value": 10.295220801812423
                  },
                  {
                    "id": "eCyU5KaacR",
                    "position": 8.333,
                    "connectedRight": true,
                    "handles": [
                      0.5,
                      1,
                      0.5,
                      0
                    ],
                    "type": "bezier",
                    "value": 6.032001973081706
                  },
                  {
                    "id": "zmDzwlztvT",
                    "position": 8.667,
                    "connectedRight": true,
                    "handles": [
                      0.5,
                      1,
                      0.5,
                      0
                    ],
                    "type": "bezier",
                    "value": -2.1710433096688506
                  },
                  {
                    "id": "z3QQRnWE1D",
                    "position": 9.367,
                    "connectedRight": true,
                    "handles": [
                      0.5,
                      1,
                      0.5,
                      0
                    ],
                    "type": "bezier",
                    "value": -2.1710433096688506
                  },
                  {
                    "id": "mJvBiGrOkY",
                    "position": 10,
                    "connectedRight": true,
                    "handles": [
                      0.5,
                      1,
                      0.5,
                      0
                    ],
                    "type": "bezier",
                    "value": -2.1710433096688506
                  }
                ]
              },
              "OUBbs33GcK": {
                "type": "BasicKeyframedTrack",
                "__debugName": "camera:[\"rotation\",\"x\"]",
                "keyframes": [
                  {
                    "id": "UsMgNf-SlI",
                    "position": 0,
                    "connectedRight": true,
                    "handles": [
                      0.5,
                      1,
                      0.5,
                      0
                    ],
                    "type": "bezier",
                    "value": 1.3884877055929437
                  },
                  {
                    "id": "PcPFcdefOf",
                    "position": 1,
                    "connectedRight": true,
                    "handles": [
                      0.5,
                      1,
                      0.5,
                      0
                    ],
                    "type": "bezier",
                    "value": 1.3393761743089114
                  },
                  {
                    "id": "eHuKM3lHsv",
                    "position": 1.7,
                    "connectedRight": true,
                    "handles": [
                      0.5,
                      1,
                      0.5,
                      0
                    ],
                    "type": "bezier",
                    "value": 1.3393761743089114
                  },
                  {
                    "id": "koxxeTbOG4",
                    "position": 2.2,
                    "connectedRight": true,
                    "handles": [
                      0.5,
                      1,
                      0.5,
                      0
                    ],
                    "type": "bezier",
                    "value": 1.3393761743089114
                  },
                  {
                    "id": "6DHCKa4v1w",
                    "position": 3.033,
                    "connectedRight": true,
                    "handles": [
                      0.5,
                      1,
                      0.5,
                      0
                    ],
                    "type": "bezier",
                    "value": -1.0746034758039231
                  },
                  {
                    "id": "fu3OMwnn-H",
                    "position": 3.5,
                    "connectedRight": true,
                    "handles": [
                      0.5,
                      1,
                      0.5,
                      0
                    ],
                    "type": "bezier",
                    "value": -1.7901940855233405
                  }
                ]
              },
              "cC4VNJJxsL": {
                "type": "BasicKeyframedTrack",
                "__debugName": "camera:[\"rotation\",\"y\"]",
                "keyframes": [
                  {
                    "id": "CgygLv8ZSq",
                    "position": 0,
                    "connectedRight": true,
                    "handles": [
                      0.5,
                      1,
                      0.5,
                      0
                    ],
                    "type": "bezier",
                    "value": -1.368576597923209
                  },
                  {
                    "id": "WrL2h3ApeI",
                    "position": 1,
                    "connectedRight": true,
                    "handles": [
                      0.5,
                      1,
                      0.5,
                      0
                    ],
                    "type": "bezier",
                    "value": -1.4101310576669481
                  },
                  {
                    "id": "K3y05Cl6L9",
                    "position": 1.7,
                    "connectedRight": true,
                    "handles": [
                      0.5,
                      1,
                      0.5,
                      0
                    ],
                    "type": "bezier",
                    "value": -1.4101310576669481
                  },
                  {
                    "id": "7bB1xxA0tU",
                    "position": 2.2,
                    "connectedRight": true,
                    "handles": [
                      0.5,
                      1,
                      0.5,
                      0
                    ],
                    "type": "bezier",
                    "value": -1.4101310576669481
                  },
                  {
                    "id": "QxWWOaEVW_",
                    "position": 3.033,
                    "connectedRight": true,
                    "handles": [
                      0.5,
                      1,
                      0.5,
                      0
                    ],
                    "type": "bezier",
                    "value": 0.7656095518564989
                  },
                  {
                    "id": "DgcE1dc_Uz",
                    "position": 3.5,
                    "connectedRight": true,
                    "handles": [
                      0.5,
                      1,
                      0.5,
                      0
                    ],
                    "type": "bezier",
                    "value": 1.4105775197046975
                  }
                ]
              },
              "zovOLtdw1u": {
                "type": "BasicKeyframedTrack",
                "__debugName": "camera:[\"rotation\",\"z\"]",
                "keyframes": [
                  {
                    "id": "qqjtoVdKJ6",
                    "position": 0,
                    "connectedRight": true,
                    "handles": [
                      0.5,
                      1,
                      0.5,
                      0
                    ],
                    "type": "bezier",
                    "value": 1.3847815812806608
                  },
                  {
                    "id": "8-MtwEcr-4",
                    "position": 1,
                    "connectedRight": true,
                    "handles": [
                      0.5,
                      1,
                      0.5,
                      0
                    ],
                    "type": "bezier",
                    "value": 1.3364655037576598
                  },
                  {
                    "id": "Q4BgQVkrRz",
                    "position": 1.7,
                    "connectedRight": true,
                    "handles": [
                      0.5,
                      1,
                      0.5,
                      0
                    ],
                    "type": "bezier",
                    "value": 1.3364655037576598
                  },
                  {
                    "id": "npWKGBfFbP",
                    "position": 2.2,
                    "connectedRight": true,
                    "handles": [
                      0.5,
                      1,
                      0.5,
                      0
                    ],
                    "type": "bezier",
                    "value": 1.3364655037576598
                  },
                  {
                    "id": "g0XGWJiAqO",
                    "position": 3.033,
                    "connectedRight": true,
                    "handles": [
                      0.5,
                      1,
                      0.5,
                      0
                    ],
                    "type": "bezier",
                    "value": 1.6888111919899924
                  },
                  {
                    "id": "5zykTBvD6m",
                    "position": 3.5,
                    "connectedRight": true,
                    "handles": [
                      0.5,
                      1,
                      0.5,
                      0
                    ],
                    "type": "bezier",
                    "value": 1.7932591585925266
                  }
                ]
              },
              "RzY3Qj-5yn": {
                "type": "BasicKeyframedTrack",
                "__debugName": "camera:[\"scale\",\"x\"]",
                "keyframes": [
                  {
                    "id": "kLUnA7X6I2",
                    "position": 0,
                    "connectedRight": true,
                    "handles": [
                      0.5,
                      1,
                      0.5,
                      0
                    ],
                    "type": "bezier",
                    "value": 1
                  },
                  {
                    "id": "ovoHsfoI8T",
                    "position": 1,
                    "connectedRight": true,
                    "handles": [
                      0.5,
                      1,
                      0.5,
                      0
                    ],
                    "type": "bezier",
                    "value": 1
                  },
                  {
                    "id": "OSSqh9NHQi",
                    "position": 1.7,
                    "connectedRight": true,
                    "handles": [
                      0.5,
                      1,
                      0.5,
                      0
                    ],
                    "type": "bezier",
                    "value": 1
                  },
                  {
                    "id": "VmXqzUQk_x",
                    "position": 2.2,
                    "connectedRight": true,
                    "handles": [
                      0.5,
                      1,
                      0.5,
                      0
                    ],
                    "type": "bezier",
                    "value": 1
                  },
                  {
                    "id": "lqWo8aFyQp",
                    "position": 3.033,
                    "connectedRight": true,
                    "handles": [
                      0.5,
                      1,
                      0.5,
                      0
                    ],
                    "type": "bezier",
                    "value": 1
                  }
                ]
              },
              "w1MW4EYcxo": {
                "type": "BasicKeyframedTrack",
                "__debugName": "camera:[\"scale\",\"y\"]",
                "keyframes": [
                  {
                    "id": "Y-6uT_2eHd",
                    "position": 0,
                    "connectedRight": true,
                    "handles": [
                      0.5,
                      1,
                      0.5,
                      0
                    ],
                    "type": "bezier",
                    "value": 1
                  },
                  {
                    "id": "Q71a3lJO4W",
                    "position": 1,
                    "connectedRight": true,
                    "handles": [
                      0.5,
                      1,
                      0.5,
                      0
                    ],
                    "type": "bezier",
                    "value": 1
                  },
                  {
                    "id": "u2d6dSy2XR",
                    "position": 1.7,
                    "connectedRight": true,
                    "handles": [
                      0.5,
                      1,
                      0.5,
                      0
                    ],
                    "type": "bezier",
                    "value": 1
                  },
                  {
                    "id": "wFWu8Jz7-b",
                    "position": 2.2,
                    "connectedRight": true,
                    "handles": [
                      0.5,
                      1,
                      0.5,
                      0
                    ],
                    "type": "bezier",
                    "value": 1
                  },
                  {
                    "id": "-YzIp6z2Ak",
                    "position": 3.033,
                    "connectedRight": true,
                    "handles": [
                      0.5,
                      1,
                      0.5,
                      0
                    ],
                    "type": "bezier",
                    "value": 1
                  }
                ]
              },
              "0YKwzcgn3y": {
                "type": "BasicKeyframedTrack",
                "__debugName": "camera:[\"scale\",\"z\"]",
                "keyframes": [
                  {
                    "id": "9n4eqOeRyN",
                    "position": 0,
                    "connectedRight": true,
                    "handles": [
                      0.5,
                      1,
                      0.5,
                      0
                    ],
                    "type": "bezier",
                    "value": 1
                  },
                  {
                    "id": "vBAPp9hUTc",
                    "position": 1,
                    "connectedRight": true,
                    "handles": [
                      0.5,
                      1,
                      0.5,
                      0
                    ],
                    "type": "bezier",
                    "value": 1
                  },
                  {
                    "id": "k2De_UHwHA",
                    "position": 1.7,
                    "connectedRight": true,
                    "handles": [
                      0.5,
                      1,
                      0.5,
                      0
                    ],
                    "type": "bezier",
                    "value": 1
                  },
                  {
                    "id": "iD9Q6YTIA-",
                    "position": 2.2,
                    "connectedRight": true,
                    "handles": [
                      0.5,
                      1,
                      0.5,
                      0
                    ],
                    "type": "bezier",
                    "value": 1
                  },
                  {
                    "id": "u39f_G7UL7",
                    "position": 3.033,
                    "connectedRight": true,
                    "handles": [
                      0.5,
                      1,
                      0.5,
                      0
                    ],
                    "type": "bezier",
                    "value": 1
                  }
                ]
              },
              "4vzRti1PSu": {
                "type": "BasicKeyframedTrack",
                "__debugName": "camera:[\"near\"]",
                "keyframes": [
                  {
                    "id": "MJY7KKpAwr",
                    "position": 0,
                    "connectedRight": true,
                    "handles": [
                      0.5,
                      1,
                      0.5,
                      0
                    ],
                    "type": "bezier",
                    "value": 0.1
                  },
                  {
                    "id": "iZk88FznnS",
                    "position": 1,
                    "connectedRight": true,
                    "handles": [
                      0.5,
                      1,
                      0.5,
                      0
                    ],
                    "type": "bezier",
                    "value": 0.1
                  },
                  {
                    "id": "5CTZ-5R_b5",
                    "position": 1.7,
                    "connectedRight": true,
                    "handles": [
                      0.5,
                      1,
                      0.5,
                      0
                    ],
                    "type": "bezier",
                    "value": 0.1
                  },
                  {
                    "id": "SOw7Ojs3d9",
                    "position": 2.2,
                    "connectedRight": true,
                    "handles": [
                      0.5,
                      1,
                      0.5,
                      0
                    ],
                    "type": "bezier",
                    "value": 0.1
                  },
                  {
                    "id": "4RqBZx0U4E",
                    "position": 3.033,
                    "connectedRight": true,
                    "handles": [
                      0.5,
                      1,
                      0.5,
                      0
                    ],
                    "type": "bezier",
                    "value": 0.1
                  }
                ]
              },
              "sjbZ7lM7bs": {
                "type": "BasicKeyframedTrack",
                "__debugName": "camera:[\"far\"]",
                "keyframes": [
                  {
                    "id": "ayHLA8psye",
                    "position": 0,
                    "connectedRight": true,
                    "handles": [
                      0.5,
                      1,
                      0.5,
                      0
                    ],
                    "type": "bezier",
                    "value": 2000
                  },
                  {
                    "id": "bo_1txkOLG",
                    "position": 1,
                    "connectedRight": true,
                    "handles": [
                      0.5,
                      1,
                      0.5,
                      0
                    ],
                    "type": "bezier",
                    "value": 2000
                  },
                  {
                    "id": "Rr9f-T1wMk",
                    "position": 1.7,
                    "connectedRight": true,
                    "handles": [
                      0.5,
                      1,
                      0.5,
                      0
                    ],
                    "type": "bezier",
                    "value": 2000
                  },
                  {
                    "id": "2RicI7-gPY",
                    "position": 2.2,
                    "connectedRight": true,
                    "handles": [
                      0.5,
                      1,
                      0.5,
                      0
                    ],
                    "type": "bezier",
                    "value": 2000
                  },
                  {
                    "id": "WMxai5ihZU",
                    "position": 3.033,
                    "connectedRight": true,
                    "handles": [
                      0.5,
                      1,
                      0.5,
                      0
                    ],
                    "type": "bezier",
                    "value": 2000
                  }
                ]
              },
              "n_efNGskFz": {
                "type": "BasicKeyframedTrack",
                "__debugName": "camera:[\"fov\"]",
                "keyframes": [
                  {
                    "id": "Ctd7UEGdAR",
                    "position": 0,
                    "connectedRight": true,
                    "handles": [
                      0.5,
                      1,
                      0.5,
                      0
                    ],
                    "type": "bezier",
                    "value": 50
                  },
                  {
                    "id": "ManuDjw2yn",
                    "position": 1,
                    "connectedRight": true,
                    "handles": [
                      0.5,
                      1,
                      0.5,
                      0
                    ],
                    "type": "bezier",
                    "value": 50
                  },
                  {
                    "id": "K4me6hsJOj",
                    "position": 1.7,
                    "connectedRight": true,
                    "handles": [
                      0.5,
                      1,
                      0.5,
                      0
                    ],
                    "type": "bezier",
                    "value": 50
                  },
                  {
                    "id": "QkEYm6d403",
                    "position": 2.2,
                    "connectedRight": true,
                    "handles": [
                      0.5,
                      1,
                      0.5,
                      0
                    ],
                    "type": "bezier",
                    "value": 50
                  },
                  {
                    "id": "zwXLNM28qU",
                    "position": 3.033,
                    "connectedRight": true,
                    "handles": [
                      0.5,
                      1,
                      0.5,
                      0
                    ],
                    "type": "bezier",
                    "value": 50
                  }
                ]
              },
              "HthzeIFH0t": {
                "type": "BasicKeyframedTrack",
                "__debugName": "camera:[\"zoom\"]",
                "keyframes": [
                  {
                    "id": "zhbgbydmbP",
                    "position": 0,
                    "connectedRight": true,
                    "handles": [
                      0.5,
                      1,
                      0.5,
                      0
                    ],
                    "type": "bezier",
                    "value": 1
                  },
                  {
                    "id": "as6QOFYNwH",
                    "position": 1,
                    "connectedRight": true,
                    "handles": [
                      0.5,
                      1,
                      0.5,
                      0
                    ],
                    "type": "bezier",
                    "value": 1
                  },
                  {
                    "id": "w-U1aNzoF7",
                    "position": 1.7,
                    "connectedRight": true,
                    "handles": [
                      0.5,
                      1,
                      0.5,
                      0
                    ],
                    "type": "bezier",
                    "value": 1
                  },
                  {
                    "id": "ubNl4SXdVu",
                    "position": 2.2,
                    "connectedRight": true,
                    "handles": [
                      0.5,
                      1,
                      0.5,
                      0
                    ],
                    "type": "bezier",
                    "value": 1
                  },
                  {
                    "id": "W93osA8FoM",
                    "position": 3.033,
                    "connectedRight": true,
                    "handles": [
                      0.5,
                      1,
                      0.5,
                      0
                    ],
                    "type": "bezier",
                    "value": 1
                  }
                ]
              }
            },
            "trackIdByPropPath": {
              "[\"position\",\"x\"]": "fpXOXqXAyG",
              "[\"position\",\"y\"]": "yohFLt71No",
              "[\"position\",\"z\"]": "W5pHjE1nGy",
              "[\"rotation\",\"x\"]": "OUBbs33GcK",
              "[\"rotation\",\"y\"]": "cC4VNJJxsL",
              "[\"rotation\",\"z\"]": "zovOLtdw1u",
              "[\"scale\",\"x\"]": "RzY3Qj-5yn",
              "[\"scale\",\"y\"]": "w1MW4EYcxo",
              "[\"scale\",\"z\"]": "0YKwzcgn3y",
              "[\"near\"]": "4vzRti1PSu",
              "[\"far\"]": "sjbZ7lM7bs",
              "[\"fov\"]": "n_efNGskFz",
              "[\"zoom\"]": "HthzeIFH0t"
            }
          },
          "extrude-path": {
            "trackData": {
              "qCzQKl3vhN": {
                "type": "BasicKeyframedTrack",
                "__debugName": "extrude-path:[\"position\",\"x\"]",
                "keyframes": []
              },
              "04e6y-UlnY": {
                "type": "BasicKeyframedTrack",
                "__debugName": "extrude-path:[\"position\",\"y\"]",
                "keyframes": []
              },
              "ds3dq5FzfM": {
                "type": "BasicKeyframedTrack",
                "__debugName": "extrude-path:[\"position\",\"z\"]",
                "keyframes": []
              },
              "mH10XzlIE9": {
                "type": "BasicKeyframedTrack",
                "__debugName": "extrude-path:[\"rotation\",\"x\"]",
                "keyframes": []
              },
              "iZaf6v9jAp": {
                "type": "BasicKeyframedTrack",
                "__debugName": "extrude-path:[\"rotation\",\"y\"]",
                "keyframes": []
              },
              "11d469pIUf": {
                "type": "BasicKeyframedTrack",
                "__debugName": "extrude-path:[\"rotation\",\"z\"]",
                "keyframes": []
              },
              "Rs3Vbj3_xu": {
                "type": "BasicKeyframedTrack",
                "__debugName": "extrude-path:[\"scale\",\"x\"]",
                "keyframes": []
              },
              "d_gHllMFOo": {
                "type": "BasicKeyframedTrack",
                "__debugName": "extrude-path:[\"scale\",\"y\"]",
                "keyframes": []
              },
              "r0yNKjNdX3": {
                "type": "BasicKeyframedTrack",
                "__debugName": "extrude-path:[\"scale\",\"z\"]",
                "keyframes": []
              }
            },
            "trackIdByPropPath": {
              "[\"position\",\"x\"]": "qCzQKl3vhN",
              "[\"position\",\"y\"]": "04e6y-UlnY",
              "[\"position\",\"z\"]": "ds3dq5FzfM",
              "[\"rotation\",\"x\"]": "mH10XzlIE9",
              "[\"rotation\",\"y\"]": "iZaf6v9jAp",
              "[\"rotation\",\"z\"]": "11d469pIUf",
              "[\"scale\",\"x\"]": "Rs3Vbj3_xu",
              "[\"scale\",\"y\"]": "d_gHllMFOo",
              "[\"scale\",\"z\"]": "r0yNKjNdX3"
            }
          },
          "potato-theathre-key": {
            "trackData": {
              "zMmr7uHePr": {
                "type": "BasicKeyframedTrack",
                "__debugName": "potato-theathre-key:[\"position\",\"x\"]",
                "keyframes": [
                  {
                    "id": "KgPLyL45OH",
                    "position": 4.4,
                    "connectedRight": true,
                    "handles": [
                      0.5,
                      1,
                      0.5,
                      0
                    ],
                    "type": "bezier",
                    "value": -6.462491101371063
                  },
                  {
                    "id": "2zlnWFeIh5",
                    "position": 4.867,
                    "connectedRight": true,
                    "handles": [
                      0.5,
                      1,
                      0.5,
                      0
                    ],
                    "type": "bezier",
                    "value": -10.483156678598188
                  },
                  {
                    "id": "PIAGUlMwa2",
                    "position": 5.133,
                    "connectedRight": true,
                    "handles": [
                      0.5,
                      1,
                      0.5,
                      0
                    ],
                    "type": "bezier",
                    "value": -18.348812057337774
                  },
                  {
                    "id": "qLgOj2MFnr",
                    "position": 5.267,
                    "connectedRight": true,
                    "handles": [
                      0.5,
                      1,
                      0.5,
                      0
                    ],
                    "type": "bezier",
                    "value": -20.534794842695447
                  },
                  {
                    "id": "m139F9Xl6-",
                    "position": 5.533,
                    "connectedRight": true,
                    "handles": [
                      0.5,
                      1,
                      0.5,
                      0
                    ],
                    "type": "bezier",
                    "value": -26.78696318381413
                  },
                  {
                    "id": "7zoIcKjo0F",
                    "position": 5.933,
                    "connectedRight": true,
                    "handles": [
                      0.5,
                      1,
                      0.5,
                      0
                    ],
                    "type": "bezier",
                    "value": -32.18725878257416
                  },
                  {
                    "id": "mpEJhvH5l6",
                    "position": 6.367,
                    "connectedRight": true,
                    "handles": [
                      0.5,
                      1,
                      0.5,
                      0
                    ],
                    "type": "bezier",
                    "value": -37.85631734859777
                  },
                  {
                    "id": "FfzsFW-50X",
                    "position": 6.5,
                    "connectedRight": true,
                    "handles": [
                      0.5,
                      1,
                      0.5,
                      0
                    ],
                    "type": "bezier",
                    "value": -42.08470753796787
                  },
                  {
                    "id": "-623B78Dxb",
                    "position": 6.767,
                    "connectedRight": true,
                    "handles": [
                      0.5,
                      1,
                      0.5,
                      0
                    ],
                    "type": "bezier",
                    "value": -51.597616238348536
                  },
                  {
                    "id": "vk6L8MqeUU",
                    "position": 7.1,
                    "connectedRight": true,
                    "handles": [
                      0.5,
                      1,
                      0.5,
                      0
                    ],
                    "type": "bezier",
                    "value": -51.597616238348536
                  },
                  {
                    "id": "3wUE-CfTrW",
                    "position": 7.133,
                    "connectedRight": true,
                    "handles": [
                      0.5,
                      1,
                      0.5,
                      0
                    ],
                    "type": "bezier",
                    "value": -55.87045924771716
                  },
                  {
                    "id": "4cOmicy8K1",
                    "position": 7.233,
                    "connectedRight": true,
                    "handles": [
                      0.5,
                      1,
                      0.5,
                      0
                    ],
                    "type": "bezier",
                    "value": -59.01516315468338
                  },
                  {
                    "id": "goL5FkGAXh",
                    "position": 7.467,
                    "connectedRight": true,
                    "handles": [
                      0.5,
                      1,
                      0.5,
                      0
                    ],
                    "type": "bezier",
                    "value": -65.64701691914993
                  },
                  {
                    "id": "dmNfffsoZe",
                    "position": 8.333,
                    "connectedRight": true,
                    "handles": [
                      0.5,
                      1,
                      0.5,
                      0
                    ],
                    "type": "bezier",
                    "value": -69.67929912831296
                  },
                  {
                    "id": "miNE0rspxY",
                    "position": 8.667,
                    "connectedRight": true,
                    "handles": [
                      0.5,
                      1,
                      0.5,
                      0
                    ],
                    "type": "bezier",
                    "value": -74.65910752458205
                  },
                  {
                    "id": "KuIHeNS_W9",
                    "position": 8.967,
                    "connectedRight": true,
                    "handles": [
                      0.5,
                      1,
                      0.5,
                      0
                    ],
                    "type": "bezier",
                    "value": -78.11661000004412
                  },
                  {
                    "id": "4IgvnyeDfp",
                    "position": 9.1,
                    "connectedRight": true,
                    "handles": [
                      0.5,
                      1,
                      0.5,
                      0
                    ],
                    "type": "bezier",
                    "value": -80.78798810015299
                  },
                  {
                    "id": "ggV-nNTCke",
                    "position": 9.367,
                    "connectedRight": true,
                    "handles": [
                      0.5,
                      1,
                      0.5,
                      0
                    ],
                    "type": "bezier",
                    "value": -85.17820253710144
                  },
                  {
                    "id": "0q9kMb3573",
                    "position": 9.567,
                    "connectedRight": true,
                    "handles": [
                      0.5,
                      1,
                      0.5,
                      0
                    ],
                    "type": "bezier",
                    "value": -89.30305294007144
                  },
                  {
                    "id": "B-2mqO21FZ",
                    "position": 9.833,
                    "connectedRight": true,
                    "handles": [
                      0.5,
                      1,
                      0.5,
                      0
                    ],
                    "type": "bezier",
                    "value": -131.04447965345352
                  },
                  {
                    "id": "WJt2O1YX37",
                    "position": 9.9,
                    "connectedRight": true,
                    "handles": [
                      0.5,
                      1,
                      0.5,
                      0
                    ],
                    "type": "bezier",
                    "value": -159.85783568325525
                  },
                  {
                    "id": "vFD4gIasV7",
                    "position": 9.933,
                    "connectedRight": true,
                    "handles": [
                      0.5,
                      1,
                      0.5,
                      0
                    ],
                    "type": "bezier",
                    "value": -181.85639353659525
                  },
                  {
                    "id": "KE7V_jpX9T",
                    "position": 10,
                    "connectedRight": true,
                    "handles": [
                      0.5,
                      1,
                      0.5,
                      0
                    ],
                    "type": "bezier",
                    "value": -273.51654336985604
                  }
                ]
              },
              "IRLyA7iBWO": {
                "type": "BasicKeyframedTrack",
                "__debugName": "potato-theathre-key:[\"position\",\"y\"]",
                "keyframes": [
                  {
                    "id": "AeZRkoFxmN",
                    "position": 4.4,
                    "connectedRight": true,
                    "handles": [
                      0.5,
                      1,
                      0.5,
                      0
                    ],
                    "type": "bezier",
                    "value": 1.5467153826051598
                  },
                  {
                    "id": "By5NqBR2Xf",
                    "position": 4.867,
                    "connectedRight": true,
                    "handles": [
                      0.5,
                      1,
                      0.5,
                      0
                    ],
                    "type": "bezier",
                    "value": 1.5467153826051598
                  },
                  {
                    "id": "wslQm_NDUY",
                    "position": 5.133,
                    "connectedRight": true,
                    "handles": [
                      0.5,
                      1,
                      0.5,
                      0
                    ],
                    "type": "bezier",
                    "value": 3.319791239196671
                  },
                  {
                    "id": "S_d2wMFoxD",
                    "position": 5.267,
                    "connectedRight": true,
                    "handles": [
                      0.5,
                      1,
                      0.5,
                      0
                    ],
                    "type": "bezier",
                    "value": 3.550241773804611
                  },
                  {
                    "id": "_B0NjyEvfH",
                    "position": 5.533,
                    "connectedRight": true,
                    "handles": [
                      0.5,
                      1,
                      0.5,
                      0
                    ],
                    "type": "bezier",
                    "value": 3.6798686947432984
                  },
                  {
                    "id": "aK2yiDR8gN",
                    "position": 5.933,
                    "connectedRight": true,
                    "handles": [
                      0.5,
                      1,
                      0.5,
                      0
                    ],
                    "type": "bezier",
                    "value": 3.444107725708957
                  },
                  {
                    "id": "5FMalUx3ls",
                    "position": 6.367,
                    "connectedRight": true,
                    "handles": [
                      0.5,
                      1,
                      0.5,
                      0
                    ],
                    "type": "bezier",
                    "value": 3.1966133586700405
                  },
                  {
                    "id": "D__IaoyhE-",
                    "position": 6.5,
                    "connectedRight": true,
                    "handles": [
                      0.5,
                      1,
                      0.5,
                      0
                    ],
                    "type": "bezier",
                    "value": 2.969678844408048
                  },
                  {
                    "id": "YgsMTLk2M4",
                    "position": 6.767,
                    "connectedRight": true,
                    "handles": [
                      0.5,
                      1,
                      0.5,
                      0
                    ],
                    "type": "bezier",
                    "value": 2.459128204931429
                  },
                  {
                    "id": "2np1R9VoMv",
                    "position": 7.1,
                    "connectedRight": true,
                    "handles": [
                      0.5,
                      1,
                      0.5,
                      0
                    ],
                    "type": "bezier",
                    "value": 2.459128204931429
                  },
                  {
                    "id": "K8SBhEIjQQ",
                    "position": 7.133,
                    "connectedRight": true,
                    "handles": [
                      0.5,
                      1,
                      0.5,
                      0
                    ],
                    "type": "bezier",
                    "value": 2.459128204931429
                  },
                  {
                    "id": "M7tuKDkQXq",
                    "position": 7.233,
                    "connectedRight": true,
                    "handles": [
                      0.5,
                      1,
                      0.5,
                      0
                    ],
                    "type": "bezier",
                    "value": 2.459128204931429
                  },
                  {
                    "id": "lDOv1xMZag",
                    "position": 7.467,
                    "connectedRight": true,
                    "handles": [
                      0.5,
                      1,
                      0.5,
                      0
                    ],
                    "type": "bezier",
                    "value": 2.459128204931429
                  },
                  {
                    "id": "005D1SnJRa",
                    "position": 8.333,
                    "connectedRight": true,
                    "handles": [
                      0.5,
                      1,
                      0.5,
                      0
                    ],
                    "type": "bezier",
                    "value": 2.459128204931429
                  },
                  {
                    "id": "WYKepBZVbX",
                    "position": 8.667,
                    "connectedRight": true,
                    "handles": [
                      0.5,
                      1,
                      0.5,
                      0
                    ],
                    "type": "bezier",
                    "value": 2.551099934075501
                  },
                  {
                    "id": "A89oENvYbS",
                    "position": 8.967,
                    "connectedRight": true,
                    "handles": [
                      0.5,
                      1,
                      0.5,
                      0
                    ],
                    "type": "bezier",
                    "value": 2.551099934075501
                  },
                  {
                    "id": "pLnAuZve9a",
                    "position": 9.1,
                    "connectedRight": true,
                    "handles": [
                      0.5,
                      1,
                      0.5,
                      0
                    ],
                    "type": "bezier",
                    "value": 2.551099934075501
                  },
                  {
                    "id": "VjtZSny6Eg",
                    "position": 9.367,
                    "connectedRight": true,
                    "handles": [
                      0.5,
                      1,
                      0.5,
                      0
                    ],
                    "type": "bezier",
                    "value": 2.567276803370084
                  },
                  {
                    "id": "v55BOS5TWp",
                    "position": 9.567,
                    "connectedRight": true,
                    "handles": [
                      0.5,
                      1,
                      0.5,
                      0
                    ],
                    "type": "bezier",
                    "value": 2.567276803370084
                  },
                  {
                    "id": "XgC66ayDrO",
                    "position": 9.833,
                    "connectedRight": true,
                    "handles": [
                      0.5,
                      1,
                      0.5,
                      0
                    ],
                    "type": "bezier",
                    "value": 3.654902517744155
                  },
                  {
                    "id": "gV2EjtXMDZ",
                    "position": 9.9,
                    "connectedRight": true,
                    "handles": [
                      0.5,
                      1,
                      0.5,
                      0
                    ],
                    "type": "bezier",
                    "value": 3.71716024030448
                  },
                  {
                    "id": "qSCDzk8bXJ",
                    "position": 9.933,
                    "connectedRight": true,
                    "handles": [
                      0.5,
                      1,
                      0.5,
                      0
                    ],
                    "type": "bezier",
                    "value": 3.541375422518369
                  },
                  {
                    "id": "nDm309wjyk",
                    "position": 10,
                    "connectedRight": true,
                    "handles": [
                      0.5,
                      1,
                      0.5,
                      0
                    ],
                    "type": "bezier",
                    "value": 3.0234578423940883
                  }
                ]
              },
              "RsYGmpCVLy": {
                "type": "BasicKeyframedTrack",
                "__debugName": "potato-theathre-key:[\"position\",\"z\"]",
                "keyframes": [
                  {
                    "id": "_RKUbtteV-",
                    "position": 4.4,
                    "connectedRight": true,
                    "handles": [
                      0.5,
                      1,
                      0.5,
                      0
                    ],
                    "type": "bezier",
                    "value": 0.31880150983661926
                  },
                  {
                    "id": "7RHhSndckS",
                    "position": 4.867,
                    "connectedRight": true,
                    "handles": [
                      0.5,
                      1,
                      0.5,
                      0
                    ],
                    "type": "bezier",
                    "value": 0.31880150983661926
                  },
                  {
                    "id": "SnJbc4SP3a",
                    "position": 5.133,
                    "connectedRight": true,
                    "handles": [
                      0.5,
                      1,
                      0.5,
                      0
                    ],
                    "type": "bezier",
                    "value": 0.7081255317223847
                  },
                  {
                    "id": "iYsI0XgSAH",
                    "position": 5.267,
                    "connectedRight": true,
                    "handles": [
                      0.5,
                      1,
                      0.5,
                      0
                    ],
                    "type": "bezier",
                    "value": 1.1564603359444545
                  },
                  {
                    "id": "pOQ6T_o7jI",
                    "position": 5.533,
                    "connectedRight": true,
                    "handles": [
                      0.5,
                      1,
                      0.5,
                      0
                    ],
                    "type": "bezier",
                    "value": 4.572175427945602
                  },
                  {
                    "id": "hC_A-cxvX7",
                    "position": 5.933,
                    "connectedRight": true,
                    "handles": [
                      0.5,
                      1,
                      0.5,
                      0
                    ],
                    "type": "bezier",
                    "value": 4.409561398482091
                  },
                  {
                    "id": "_Gf2TCupr7",
                    "position": 6.367,
                    "connectedRight": true,
                    "handles": [
                      0.5,
                      1,
                      0.5,
                      0
                    ],
                    "type": "bezier",
                    "value": 3.307438079868999
                  },
                  {
                    "id": "igbX24Bw6d",
                    "position": 6.5,
                    "connectedRight": true,
                    "handles": [
                      0.5,
                      1,
                      0.5,
                      0
                    ],
                    "type": "bezier",
                    "value": 2.601963690570873
                  },
                  {
                    "id": "XxwNUbE_Mg",
                    "position": 6.767,
                    "connectedRight": true,
                    "handles": [
                      0.5,
                      1,
                      0.5,
                      0
                    ],
                    "type": "bezier",
                    "value": 1.0698956463639082
                  },
                  {
                    "id": "4lA4syb4n3",
                    "position": 7.1,
                    "connectedRight": true,
                    "handles": [
                      0.5,
                      1,
                      0.5,
                      0
                    ],
                    "type": "bezier",
                    "value": 0.9041730678293294
                  },
                  {
                    "id": "T3eaOzECHD",
                    "position": 7.133,
                    "connectedRight": true,
                    "handles": [
                      0.5,
                      1,
                      0.5,
                      0
                    ],
                    "type": "bezier",
                    "value": 0.92032647938763
                  },
                  {
                    "id": "3omBHjAXFI",
                    "position": 7.233,
                    "connectedRight": true,
                    "handles": [
                      0.5,
                      1,
                      0.5,
                      0
                    ],
                    "type": "bezier",
                    "value": 0.9721436672488533
                  },
                  {
                    "id": "20KtUHwFCL",
                    "position": 7.467,
                    "connectedRight": true,
                    "handles": [
                      0.5,
                      1,
                      0.5,
                      0
                    ],
                    "type": "bezier",
                    "value": 1.1887555792873368
                  },
                  {
                    "id": "70de_kAVpn",
                    "position": 8.333,
                    "connectedRight": true,
                    "handles": [
                      0.5,
                      1,
                      0.5,
                      0
                    ],
                    "type": "bezier",
                    "value": 0.9660442402862999
                  },
                  {
                    "id": "jVgvuIqtkM",
                    "position": 8.667,
                    "connectedRight": true,
                    "handles": [
                      0.5,
                      1,
                      0.5,
                      0
                    ],
                    "type": "bezier",
                    "value": -1.0480593828754299
                  },
                  {
                    "id": "IifujH07LK",
                    "position": 8.967,
                    "connectedRight": true,
                    "handles": [
                      0.5,
                      1,
                      0.5,
                      0
                    ],
                    "type": "bezier",
                    "value": -1.624174728282112
                  },
                  {
                    "id": "juKio12MYi",
                    "position": 9.1,
                    "connectedRight": true,
                    "handles": [
                      0.5,
                      1,
                      0.5,
                      0
                    ],
                    "type": "bezier",
                    "value": -1.3096303347063756
                  },
                  {
                    "id": "Ru6zzjjZF0",
                    "position": 9.367,
                    "connectedRight": true,
                    "handles": [
                      0.5,
                      1,
                      0.5,
                      0
                    ],
                    "type": "bezier",
                    "value": -0.19917516586490325
                  },
                  {
                    "id": "tj887brTi_",
                    "position": 9.567,
                    "connectedRight": true,
                    "handles": [
                      0.5,
                      1,
                      0.5,
                      0
                    ],
                    "type": "bezier",
                    "value": 0.6995053211949087
                  },
                  {
                    "id": "FWA75BdFd5",
                    "position": 9.833,
                    "connectedRight": true,
                    "handles": [
                      0.5,
                      1,
                      0.5,
                      0
                    ],
                    "type": "bezier",
                    "value": 0.8438348193538142
                  },
                  {
                    "id": "lndDe969F7",
                    "position": 9.9,
                    "connectedRight": true,
                    "handles": [
                      0.5,
                      1,
                      0.5,
                      0
                    ],
                    "type": "bezier",
                    "value": 0.8624592595205343
                  },
                  {
                    "id": "hNBMRkW-SF",
                    "position": 9.933,
                    "connectedRight": true,
                    "handles": [
                      0.5,
                      1,
                      0.5,
                      0
                    ],
                    "type": "bezier",
                    "value": 0.8766787355187448
                  },
                  {
                    "id": "GfkJ5rxLMm",
                    "position": 10,
                    "connectedRight": true,
                    "handles": [
                      0.5,
                      1,
                      0.5,
                      0
                    ],
                    "type": "bezier",
                    "value": 0.9093459904698578
                  }
                ]
              },
              "AyEnyO-gcK": {
                "type": "BasicKeyframedTrack",
                "__debugName": "potato-theathre-key:[\"rotation\",\"x\"]",
                "keyframes": [
                  {
                    "id": "9qtaohkE_U",
                    "position": 4.4,
                    "connectedRight": true,
                    "handles": [
                      0.5,
                      1,
                      0.5,
                      0
                    ],
                    "type": "bezier",
                    "value": 0
                  },
                  {
                    "id": "u8ViAzEfQw",
                    "position": 4.867,
                    "connectedRight": true,
                    "handles": [
                      0.5,
                      1,
                      0.5,
                      0
                    ],
                    "type": "bezier",
                    "value": 0
                  },
                  {
                    "id": "TSXicvFhbU",
                    "position": 5.033,
                    "connectedRight": true,
                    "handles": [
                      0.5,
                      1,
                      0.5,
                      0
                    ],
                    "type": "bezier",
                    "value": -0.0036665907091429084
                  },
                  {
                    "id": "InYTGZh5Bx",
                    "position": 5.267,
                    "connectedRight": true,
                    "handles": [
                      0.5,
                      1,
                      0.5,
                      0
                    ],
                    "type": "bezier",
                    "value": -0.01810653596517294
                  },
                  {
                    "id": "D5cghIpdC8",
                    "position": 5.533,
                    "connectedRight": true,
                    "handles": [
                      0.5,
                      1,
                      0.5,
                      0
                    ],
                    "type": "bezier",
                    "value": -0.03188748908031007
                  },
                  {
                    "id": "NI7oaQz-VD",
                    "position": 6.367,
                    "connectedRight": true,
                    "handles": [
                      0.5,
                      1,
                      0.5,
                      0
                    ],
                    "type": "bezier",
                    "value": -0.032336307076226464
                  },
                  {
                    "id": "l3jzfuaylu",
                    "position": 7.467,
                    "connectedRight": true,
                    "handles": [
                      0.5,
                      1,
                      0.5,
                      0
                    ],
                    "type": "bezier",
                    "value": -0.04794953915213615
                  },
                  {
                    "id": "9ba2sAmv1N",
                    "position": 8.333,
                    "connectedRight": true,
                    "handles": [
                      0.5,
                      1,
                      0.5,
                      0
                    ],
                    "type": "bezier",
                    "value": -0.1659271668344651
                  },
                  {
                    "id": "MrIQze2kb-",
                    "position": 8.967,
                    "connectedRight": true,
                    "handles": [
                      0.5,
                      1,
                      0.5,
                      0
                    ],
                    "type": "bezier",
                    "value": 0.19859745190219638
                  },
                  {
                    "id": "ww8jrdDtVS",
                    "position": 9.1,
                    "connectedRight": true,
                    "handles": [
                      0.5,
                      1,
                      0.5,
                      0
                    ],
                    "type": "bezier",
                    "value": 0.20127126612333776
                  },
                  {
                    "id": "xqBKVTddVK",
                    "position": 9.367,
                    "connectedRight": true,
                    "handles": [
                      0.5,
                      1,
                      0.5,
                      0
                    ],
                    "type": "bezier",
                    "value": 0.17539460744627228
                  },
                  {
                    "id": "q_mgg8a930",
                    "position": 9.567,
                    "connectedRight": true,
                    "handles": [
                      0.5,
                      1,
                      0.5,
                      0
                    ],
                    "type": "bezier",
                    "value": -0.060563725625334575
                  }
                ]
              },
              "J2psR2fodF": {
                "type": "BasicKeyframedTrack",
                "__debugName": "potato-theathre-key:[\"rotation\",\"y\"]",
                "keyframes": [
                  {
                    "id": "DiQaCoMxcI",
                    "position": 4.4,
                    "connectedRight": true,
                    "handles": [
                      0.5,
                      1,
                      0.5,
                      0
                    ],
                    "type": "bezier",
                    "value": 0
                  },
                  {
                    "id": "M_zfkypnAP",
                    "position": 4.867,
                    "connectedRight": true,
                    "handles": [
                      0.5,
                      1,
                      0.5,
                      0
                    ],
                    "type": "bezier",
                    "value": 0
                  },
                  {
                    "id": "d5kMrma9OD",
                    "position": 5.033,
                    "connectedRight": true,
                    "handles": [
                      0.5,
                      1,
                      0.5,
                      0
                    ],
                    "type": "bezier",
                    "value": 0.00048308587428677255
                  },
                  {
                    "id": "cjI6mBqQAU",
                    "position": 5.267,
                    "connectedRight": true,
                    "handles": [
                      0.5,
                      1,
                      0.5,
                      0
                    ],
                    "type": "bezier",
                    "value": 0.26890351106220195
                  },
                  {
                    "id": "A56B4wGDR8",
                    "position": 5.533,
                    "connectedRight": true,
                    "handles": [
                      0.5,
                      1,
                      0.5,
                      0
                    ],
                    "type": "bezier",
                    "value": -0.0003996987482595541
                  },
                  {
                    "id": "QYoYdzDkrg",
                    "position": 6.367,
                    "connectedRight": true,
                    "handles": [
                      0.5,
                      1,
                      0.5,
                      0
                    ],
                    "type": "bezier",
                    "value": -0.16677672940183394
                  },
                  {
                    "id": "Van7i0Of1m",
                    "position": 7.467,
                    "connectedRight": true,
                    "handles": [
                      0.5,
                      1,
                      0.5,
                      0
                    ],
                    "type": "bezier",
                    "value": -0.16300811643022897
                  },
                  {
                    "id": "qG-9wrtAJi",
                    "position": 8.333,
                    "connectedRight": true,
                    "handles": [
                      0.5,
                      1,
                      0.5,
                      0
                    ],
                    "type": "bezier",
                    "value": -0.16300811643022894
                  },
                  {
                    "id": "uRXo3DgkHl",
                    "position": 8.967,
                    "connectedRight": true,
                    "handles": [
                      0.5,
                      1,
                      0.5,
                      0
                    ],
                    "type": "bezier",
                    "value": -0.0807340452915398
                  },
                  {
                    "id": "Ffz7cZz8RS",
                    "position": 9.1,
                    "connectedRight": true,
                    "handles": [
                      0.5,
                      1,
                      0.5,
                      0
                    ],
                    "type": "bezier",
                    "value": 0.18043793826673502
                  },
                  {
                    "id": "jSDg6QLsOf",
                    "position": 9.367,
                    "connectedRight": true,
                    "handles": [
                      0.5,
                      1,
                      0.5,
                      0
                    ],
                    "type": "bezier",
                    "value": 0.20566668161212426
                  },
                  {
                    "id": "c1IfK4Mmfa",
                    "position": 9.567,
                    "connectedRight": true,
                    "handles": [
                      0.5,
                      1,
                      0.5,
                      0
                    ],
                    "type": "bezier",
                    "value": 0.020012011528689505
                  }
                ]
              },
              "MlPbmZD2_q": {
                "type": "BasicKeyframedTrack",
                "__debugName": "potato-theathre-key:[\"rotation\",\"z\"]",
                "keyframes": [
                  {
                    "id": "nuxPgadM4s",
                    "position": 4.4,
                    "connectedRight": true,
                    "handles": [
                      0.5,
                      1,
                      0.5,
                      0
                    ],
                    "type": "bezier",
                    "value": 0
                  },
                  {
                    "id": "pgy-aN2nBH",
                    "position": 4.867,
                    "connectedRight": true,
                    "handles": [
                      0.5,
                      1,
                      0.5,
                      0
                    ],
                    "type": "bezier",
                    "value": -0.06932419625838568
                  },
                  {
                    "id": "6JHhJKCViv",
                    "position": 5.033,
                    "connectedRight": true,
                    "handles": [
                      0.5,
                      1,
                      0.5,
                      0
                    ],
                    "type": "bezier",
                    "value": -0.1953602478287967
                  },
                  {
                    "id": "R34E6s-Qrm",
                    "position": 5.267,
                    "connectedRight": true,
                    "handles": [
                      0.5,
                      1,
                      0.5,
                      0
                    ],
                    "type": "bezier",
                    "value": -0.12314953946134438
                  },
                  {
                    "id": "qU-yYlrWPY",
                    "position": 5.533,
                    "connectedRight": true,
                    "handles": [
                      0.5,
                      1,
                      0.5,
                      0
                    ],
                    "type": "bezier",
                    "value": 0.08417965089129585
                  },
                  {
                    "id": "Zc_O4weV7h",
                    "position": 6.367,
                    "connectedRight": true,
                    "handles": [
                      0.5,
                      1,
                      0.5,
                      0
                    ],
                    "type": "bezier",
                    "value": 0.07882260248411113
                  },
                  {
                    "id": "gePs9mhtOU",
                    "position": 7.467,
                    "connectedRight": true,
                    "handles": [
                      0.5,
                      1,
                      0.5,
                      0
                    ],
                    "type": "bezier",
                    "value": -0.016225372445477282
                  },
                  {
                    "id": "GfwRNxnj_b",
                    "position": 8.333,
                    "connectedRight": true,
                    "handles": [
                      0.5,
                      1,
                      0.5,
                      0
                    ],
                    "type": "bezier",
                    "value": -0.016225372445477282
                  },
                  {
                    "id": "2D0m9bBUN1",
                    "position": 8.967,
                    "connectedRight": true,
                    "handles": [
                      0.5,
                      1,
                      0.5,
                      0
                    ],
                    "type": "bezier",
                    "value": -0.03298963731982195
                  },
                  {
                    "id": "bGz3S7qCMA",
                    "position": 9.1,
                    "connectedRight": true,
                    "handles": [
                      0.5,
                      1,
                      0.5,
                      0
                    ],
                    "type": "bezier",
                    "value": -0.08581802722753981
                  },
                  {
                    "id": "4YgxATVXn0",
                    "position": 9.367,
                    "connectedRight": true,
                    "handles": [
                      0.5,
                      1,
                      0.5,
                      0
                    ],
                    "type": "bezier",
                    "value": 0.048850720599285954
                  },
                  {
                    "id": "d4sts4iaEG",
                    "position": 9.567,
                    "connectedRight": true,
                    "handles": [
                      0.5,
                      1,
                      0.5,
                      0
                    ],
                    "type": "bezier",
                    "value": -0.00006007587009729948
                  }
                ]
              },
              "m-PTGkI41T": {
                "type": "BasicKeyframedTrack",
                "__debugName": "potato-theathre-key:[\"scale\",\"x\"]",
                "keyframes": [
                  {
                    "id": "p1fsOs2SQl",
                    "position": 4.4,
                    "connectedRight": true,
                    "handles": [
                      0.5,
                      1,
                      0.5,
                      0
                    ],
                    "type": "bezier",
                    "value": 1
                  },
                  {
                    "id": "Rzz3EY6-In",
                    "position": 10,
                    "connectedRight": true,
                    "handles": [
                      0.5,
                      1,
                      0.5,
                      0
                    ],
                    "type": "bezier",
                    "value": 1
                  }
                ]
              },
              "0syuMi57L_": {
                "type": "BasicKeyframedTrack",
                "__debugName": "potato-theathre-key:[\"scale\",\"y\"]",
                "keyframes": [
                  {
                    "id": "jAErird64S",
                    "position": 4.4,
                    "connectedRight": true,
                    "handles": [
                      0.5,
                      1,
                      0.5,
                      0
                    ],
                    "type": "bezier",
                    "value": 1
                  },
                  {
                    "id": "ztqbVL1vRc",
                    "position": 9.9,
                    "connectedRight": true,
                    "handles": [
                      0.5,
                      1,
                      0.5,
                      0
                    ],
                    "type": "bezier",
                    "value": 1
                  },
                  {
                    "id": "7pHCqli9bY",
                    "position": 10,
                    "connectedRight": true,
                    "handles": [
                      0.5,
                      1,
                      0.5,
                      0
                    ],
                    "type": "bezier",
                    "value": 0.6098539628251026
                  }
                ]
              },
              "np4M7IbeIZ": {
                "type": "BasicKeyframedTrack",
                "__debugName": "potato-theathre-key:[\"scale\",\"z\"]",
                "keyframes": [
                  {
                    "id": "8AsjkgW_DT",
                    "position": 4.4,
                    "connectedRight": true,
                    "handles": [
                      0.5,
                      1,
                      0.5,
                      0
                    ],
                    "type": "bezier",
                    "value": 1
                  },
                  {
                    "id": "WZYxI2eUKy",
                    "position": 9.9,
                    "connectedRight": true,
                    "handles": [
                      0.5,
                      1,
                      0.5,
                      0
                    ],
                    "type": "bezier",
                    "value": 1
                  },
                  {
                    "id": "oxJ9g8ZTqe",
                    "position": 10,
                    "connectedRight": true,
                    "handles": [
                      0.5,
                      1,
                      0.5,
                      0
                    ],
                    "type": "bezier",
                    "value": 0.6150779887521142
                  }
                ]
              }
            },
            "trackIdByPropPath": {
              "[\"position\",\"x\"]": "zMmr7uHePr",
              "[\"position\",\"y\"]": "IRLyA7iBWO",
              "[\"position\",\"z\"]": "RsYGmpCVLy",
              "[\"rotation\",\"x\"]": "AyEnyO-gcK",
              "[\"rotation\",\"y\"]": "J2psR2fodF",
              "[\"rotation\",\"z\"]": "MlPbmZD2_q",
              "[\"scale\",\"x\"]": "m-PTGkI41T",
              "[\"scale\",\"y\"]": "0syuMi57L_",
              "[\"scale\",\"z\"]": "np4M7IbeIZ"
            }
          }
        }
      }
    }
  },
  "definitionVersion": "0.4.0",
  "revisionHistory": [
    "Np1Zu9eluQ4Ibubr",
    "X8ZAI18u9h4i0Y_R"
  ]
}